alfred_rfc/__init__.py
alfred_rfc/rfc_list.json
alfred_rfc/search.py
alfred_rfc-0.2.2.dist-info/DESCRIPTION.rst
alfred_rfc-0.2.2.dist-info/METADATA
alfred_rfc-0.2.2.dist-info/RECORD
alfred_rfc-0.2.2.dist-info/WHEEL
alfred_rfc-0.2.2.dist-info/entry_points.txt
alfred_rfc-0.2.2.dist-info/metadata.json
alfred_rfc-0.2.2.dist-info/top_level.txt
